oveya/__init__.py
oveya/ctx.py
oveya/enums.py
oveya/errors.py
oveya/helpers.py
oveya/logging.py
oveya/models.py
oveya/request.py
oveya-0.1.28.dist-info/LICENSE.txt
oveya-0.1.28.dist-info/METADATA
oveya-0.1.28.dist-info/WHEEL
oveya-0.1.28.dist-info/top_level.txt
oveya-0.1.28.dist-info/RECORD
