Metadata-Version: 2.1
Name: oveya
Version: 0.1.28
Summary: A nano-framework for deploying Python functions as APIs on AWS Lambda using Function URLs.
Author: Spencer Porter
Requires-Python: >=3.6
License-File: LICENSE.txt
Requires-Dist: pydantic (==2.6.4)
